MANIFEST.in
README.md
setup.py
talkzoho/__init__.py
talkzoho/regions.py
talkzoho/resource.py
talkzoho/service_client.py
talkzoho/utils.py
talkzoho.egg-info/PKG-INFO
talkzoho.egg-info/SOURCES.txt
talkzoho.egg-info/dependency_links.txt
talkzoho.egg-info/requires.txt
talkzoho.egg-info/top_level.txt
talkzoho/books/__init__.py
talkzoho/books/base_resource.py
talkzoho/books/books_client.py
talkzoho/crm/__init__.py
talkzoho/crm/crm_client.py
talkzoho/crm/crm_resource.py
talkzoho/crm/utils.py
talkzoho/projects/__init__.py
talkzoho/projects/base_resource.py
talkzoho/projects/log_resource.py
talkzoho/projects/portal_resource.py
talkzoho/projects/project_resource.py
talkzoho/projects/projects_client.py
talkzoho/projects/utils.py
talkzoho/support/__init__.py
talkzoho/support/base_resource.py
talkzoho/support/support_client.py
talkzoho/support/utils.py