Metadata-Version: 1.0
Name: talkzoho
Version: 2.0.8
Summary: Asynchronous wrapper for Zoho's numerous APIs
Home-page: https://github.com/A2Z-Cloud/Talk-Zoho
Author: James Stidard
Author-email: james.stidard@a2zcloud.com
License: UNKNOWN
Keywords: talkzoho,Zoho,async,tornado
Platform: UNKNOWN
